{
  "locale": "en",
  "language": "English",
  "type": "page",
  "slug": "home-page",
  "source_file": "Home Page\\ENGLISH.docx",
  "blocks": [
    {
      "heading": "Home",
      "body": []
    },
    {
      "heading": "About Us",
      "body": []
    },
    {
      "heading": "Services",
      "body": []
    },
    {
      "heading": "Portfolio",
      "body": []
    },
    {
      "heading": "Blogs",
      "body": []
    },
    {
      "heading": "Contact",
      "body": [
        "Film & Video Production services in Egypt and MENA.",
        "Our Work."
      ]
    },
    {
      "heading": "Contact us for Next project",
      "body": []
    },
    {
      "heading": "Get a quote in 24h",
      "body": []
    },
    {
      "heading": "The Untold Story delivers the full production cycle",
      "body": [
        "Film, video, advertising, documentaries, corporate content, TV shows, and more."
      ]
    },
    {
      "heading": "Planning • Filming • Live • Post & final delivery • Localization",
      "body": [
        "With offices in Egypt Media Production City, Dubai, and Jeddah serving MENA and clients worldwide."
      ]
    },
    {
      "heading": "Projects done by The Untold Story",
      "body": []
    },
    {
      "heading": "Our Storytelling & Production Expertise",
      "body": []
    },
    {
      "heading": "Documentary Production",
      "body": []
    },
    {
      "heading": "Corporate Content",
      "body": []
    },
    {
      "heading": "Commercial & Ads",
      "body": []
    },
    {
      "heading": "Post Production",
      "body": []
    },
    {
      "heading": "Dubbing & Localizing",
      "body": []
    },
    {
      "heading": "Photography",
      "body": []
    },
    {
      "heading": "Event Coverage",
      "body": []
    },
    {
      "heading": "More services for your needs. Get in touch",
      "body": []
    },
    {
      "heading": "Where story meets execution",
      "body": [
        "Predictable budgets. Premium results."
      ]
    },
    {
      "heading": "On-Ground Production",
      "body": [
        "Original IP Development",
        "Commercial Advertising Production",
        "Documentary Production",
        "Post Production Services"
      ]
    },
    {
      "heading": "Trusted by the Titans",
      "body": [
        "Photography that matches the film.",
        "Campaign stills, event coverage, portraits, and product and food photography shot to align with your video deliverables."
      ]
    },
    {
      "heading": "Polished and aligned with your tone",
      "body": [
        "Fill out the form",
        "Get a call back",
        "Get your project done"
      ]
    },
    {
      "heading": "Creative Creations",
      "body": []
    },
    {
      "heading": "Behind every Frame",
      "body": []
    },
    {
      "heading": "News & Insights",
      "body": []
    },
    {
      "heading": "Company news and updates",
      "body": [
        "Let’s make it happen. Get in touch now!"
      ]
    },
    {
      "heading": "About",
      "body": []
    },
    {
      "heading": "About us",
      "body": [
        "Our Portfolio",
        "Get in touch"
      ]
    },
    {
      "heading": "Other pages",
      "body": []
    },
    {
      "heading": "Documentary Production",
      "body": [
        "Original IP Development",
        "Podcast Production",
        "Photography"
      ]
    },
    {
      "heading": "Email address",
      "body": [
        "bendary@globaluntoldstory.com"
      ]
    },
    {
      "heading": "Egypt",
      "body": [
        "Egyptian Media Production City",
        "+201001299639"
      ]
    },
    {
      "heading": "UAE",
      "body": [
        "UAE – Dubai – Business Bay",
        "+971547711772"
      ]
    }
  ]
}